ckonlpy/__init__.py
ckonlpy/dictionary.py
ckonlpy/utils.py
ckonlpy/custom_tag/__init__.py
ckonlpy/custom_tag/_evaluator.py
ckonlpy/custom_tag/_template.py
ckonlpy/data/__init__.py
ckonlpy/data/tagset.py
ckonlpy/data/templates/twitter_templates0
ckonlpy/data/twitter/name/nic_사람이름_v0.51.txt
ckonlpy/data/twitter/nic/won_corpus_v0.2.txt
ckonlpy/data/twitter/nic/숫자단위.txt
ckonlpy/data/twitter/not_use/congress.txt
ckonlpy/data/twitter/not_use/entities.txt
ckonlpy/data/twitter/not_use/foreign.txt
ckonlpy/data/twitter/not_use/josa.txt
ckonlpy/data/twitter/not_use/kpop.txt
ckonlpy/data/twitter/not_use/lol.txt
ckonlpy/data/twitter/not_use/modifier.txt
ckonlpy/data/twitter/not_use/names.txt
ckonlpy/data/twitter/not_use/nouns.txt
ckonlpy/data/twitter/not_use/pokemon.txt
ckonlpy/data/twitter/not_use/profane.txt
ckonlpy/data/twitter/not_use/slangs.txt
ckonlpy/data/twitter/not_use/spam.txt
ckonlpy/data/twitter/not_use/twitter.txt
ckonlpy/data/twitter/not_use/wikipedia_title_nouns.txt
ckonlpy/data/twitter/noun/company_names.txt
ckonlpy/data/twitter/noun/geolocations.txt
ckonlpy/tag/__init__.py
ckonlpy/tag/_abstract.py
ckonlpy/tag/_postprocess.py
ckonlpy/tag/_twitter.py
ats_ckonlpy-1.0.1.dist-info/LICENSE
ats_ckonlpy-1.0.1.dist-info/METADATA
ats_ckonlpy-1.0.1.dist-info/WHEEL
ats_ckonlpy-1.0.1.dist-info/top_level.txt
ats_ckonlpy-1.0.1.dist-info/RECORD
