Metadata-Version: 2.1
Name: ats-ckonlpy
Version: 1.0.1
Summary: KoNLPy wrapping package
Home-page: https://github.com/whfh3900/ats_ckonlpy.git
Author: csu5216
Author-email: csu5216@gmail.com
Classifier: Programming Language :: Python :: 3.8
Classifier: License :: OSI Approved :: GNU General Public License v3 (GPLv3)
Classifier: Operating System :: OS Independent
License-File: LICENSE
Requires-Dist: Jpype1 >=0.6.1
Requires-Dist: konlpy >=0.4.4
